.gitignore
.travis.yml
CHANGES.txt
LICENSE.txt
README.txt
setup.py
tox.ini
upgrade-resources.sh
js/__init__.py
js.jquery_maskmoney.egg-info/PKG-INFO
js.jquery_maskmoney.egg-info/SOURCES.txt
js.jquery_maskmoney.egg-info/dependency_links.txt
js.jquery_maskmoney.egg-info/entry_points.txt
js.jquery_maskmoney.egg-info/namespace_packages.txt
js.jquery_maskmoney.egg-info/not-zip-safe
js.jquery_maskmoney.egg-info/requires.txt
js.jquery_maskmoney.egg-info/top_level.txt
js/jquery_maskmoney/__init__.py
js/jquery_maskmoney/test_jquery-maskmoney.txt
js/jquery_maskmoney/resources/jquery.maskMoney.js
js/jquery_maskmoney/resources/jquery.maskMoney.min.js